{"headers": {"status": {"$": "success"}, "code": {"$": "200"}, "message": {"$": "ok"}}, "mods": {"version": "3.4", "schemaLocation": "http://www.loc.gov/mods/v3 http://www.loc.gov/standards/mods/v3/mods-3-4.xsd", "titleInfo": {"authority": "", "lang": "", "script": "", "type": "", "usage": "primary", "title": {"$": "Tenements and row houses photographed from Jacob Ruppert mansion (5th Av & 93rd St)"}}, "typeOfResource": {"collection": "yes", "usage": "primary", "$": "still image"}, "genre": {"authority": "lctgm", "valueURI": "http://id.loc.gov/vocabulary/graphicMaterials/tgm007721", "$": "Photographs"}, "originInfo": {"dateCreated": {"encoding": "w3cdtf", "keyDate": "yes", "$": "1882"}}, "subject": [{"valueURI": "http://id.loc.gov/authorities/names/n79007751", "geographic": {"authority": "naf", "valueURI": "http://id.loc.gov/authorities/names/n79007751", "$": "New York (N.Y.)"}}, {"authority": "", "geographic": {"valueURI": "http://www.geonames.org/5128581", "$": "New York City"}}, {"authority": "", "geographic": {"$": "Park Av-E 93rd St-E 94th St"}}], "identifier": [{"displayLabel": "NYPL catalog ID (B-number)", "type": "local_bnumber", "$": "pending"}, {"type": "uuid", "$": "c86c4100-b462-0132-4804-58d385a7bbd0"}], "location": {"physicalLocation": [{"authority": "marcorg", "type": "repository", "$": "nn"}, {"type": "division", "$": "Irma and Paul Milstein Division of United States History, Local History and Genealogy"}, {"type": "division_short_name", "$": "Milstein Division"}, {"type": "code", "$": "LHG"}]}, "relatedItem": {"type": "host", "titleInfo": {"title": {"$": "Tenements and row houses on Park Ave."}}, "identifier": {"type": "uuid", "$": "a00b4370-b462-0132-b8a9-58d385a7bbd0"}, "relatedItem": {"type": "host", "titleInfo": {"title": {"$": "Scrapbooks of New York City views Volume 29"}}, "identifier": {"type": "uuid", "$": "bc6c8400-b3d2-0132-f451-58d385a7b928"}, "relatedItem": {"type": "host", "titleInfo": {"title": {"$": "Scrapbooks of New York City views"}}, "identifier": [{"type": "uuid", "$": "530a11c0-c8b6-0131-2d6e-58d385a7b928"}, {"type": "local_bnumber", "$": "pending"}]}}}}, "numResults": {"$": "1"}, "capture": {"uuid": {"$": "c91a6ca0-b462-0132-b9ba-58d385a7bbd0"}, "apiUri": {"$": "http://api.repo.nypl.org/api/v1/items/mods/c91a6ca0-b462-0132-b9ba-58d385a7bbd0"}, "typeOfResource": {"$": "still image"}, "imageID": {"$": "5255152"}, "sortString": {"$": "0000000001|0000000022|0000000009|0000000001|0000000001"}, "itemLink": {"$": "http://digitalcollections.nypl.org/items/c91a6ca0-b462-0132-b9ba-58d385a7bbd0"}, "highResLink": {"$": "http://link.nypl.org/KrQl-G5YQn--ggSUmmh0AQ_"}, "orderInSequence": {"$": "1"}, "isPartOfSequence": {"$": "false"}, "totalInSequence": {"$": "1"}, "title": {"$": "Tenements and row houses photographed from Jacob Ruppert mansion (5th Av & 93rd St)"}, "rightsStatement": {"$": "The New York Public Library believes that this item is in the public domain under the laws of the United States, but did not make a determination as to its copyright status under the copyright laws of other countries. This item may not be in the public domain under the laws of other countries. Though not required, if you want to credit us as the source, please use the following statement, \"From The New York Public Library,\" and provide a link back to the item on our Digital Collections site. Doing so helps us track how our collection is used and helps justify freely releasing even more content in the future."}, "rightsStatementURI": {"$": "http://rightsstatements.org/vocab/NoC-US/1.0/"}}}